jsett/__init__.py
jsett-0.1.0.dist-info/METADATA
jsett-0.1.0.dist-info/WHEEL
jsett-0.1.0.dist-info/licenses/LICENSE
jsett-0.1.0.dist-info/RECORD
