Metadata-Version: 2.4
Name: jsett
Version: 0.1.0
Summary: A tool to read jsett files
Author-email: jaz <jaz.allibhai@gmail.com>
License-File: LICENSE
Requires-Python: >=3.9
